Workbook
Name Price: Assumptions!$B$7

Sheet Assumptions
A1: Parameter | B1: Value | C1: Unit
A3: Initial Customers | B3: 100 | C3: Customers
F4: Contribution margin = Price − Variable Cost
A5: Monthly Growth Rate | B5: 0.06 | C5: %
A7: Price per Customer | B7: 500 | C7: ₹
A9: Variable Cost per Customer | B9: 150 | C9: ₹
A11: Fixed Monthly Cost | B11: 20000 | C11: ₹
A13: Marketing Cost | B13: 8000 | C13: ₹
A15: Tax Rate | B15: 0.25 | C15: %
A17: Forecast Period (Months) | B17: 36 | C17: Months
A19: Monthly Churn Rate | B19: 0.03 | C19: %
A21: Starting Cash | B21: 500000

Sheet Customer_Model
A1: Month | B1: Customers Start | C1: New Customers | D1: Churned Customers | E1: Customers End
A3: =Revenue_Model!A3 -> 1 | B3: =Assumptions!$B$3 -> 100 | C3: =B3*Assumptions!$B$5 -> 6 | D3: =B3*Assumptions!$B$19 -> 3 | E3: =B3+C3-D3 -> 103
A4: =A3+1 -> 2 | B4: =E3 -> 103 | C4: =B4*Assumptions!$B$5 -> 6.18 | D4: =B4*Assumptions!$B$19 -> 3.09 | E4: =B4+C4-D4 -> 106.09
A5: =A4+1 -> 3 | B5: =E4 -> 106.09 | C5: =B5*Assumptions!$B$5 -> 6.3654 | D5: =B5*Assumptions!$B$19 -> 3.1827 | E5: =B5+C5-D5 -> 109.2727
A6: =A5+1 -> 4 | B6: =E5 -> 109.2727 | C6: =B6*Assumptions!$B$5 -> 6.556362 | D6: =B6*Assumptions!$B$19 -> 3.278181 | E6: =B6+C6-D6 -> 112.55088
A7: =A6+1 -> 5 | B7: =E6 -> 112.55088 | C7: =B7*Assumptions!$B$5 -> 6.7530529 | D7: =B7*Assumptions!$B$19 -> 3.3765264 | E7: =B7+C7-D7 -> 115.92741
A8: =A7+1 -> 6 | B8: =E7 -> 115.92741 | C8: =B8*Assumptions!$B$5 -> 6.9556444 | D8: =B8*Assumptions!$B$19 -> 3.4778222 | E8: =B8+C8-D8 -> 119.40523
A9: =A8+1 -> 7 | B9: =E8 -> 119.40523 | C9: =B9*Assumptions!$B$5 -> 7.1643138 | D9: =B9*Assumptions!$B$19 -> 3.5821569 | E9: =B9+C9-D9 -> 122.98739
A10: =A9+1 -> 8 | B10: =E9 -> 122.98739 | C10: =B10*Assumptions!$B$5 -> 7.3792432 | D10: =B10*Assumptions!$B$19 -> 3.6896216 | E10: =B10+C10-D10 -> 126.67701
A11: =A10+1 -> 9 | B11: =E10 -> 126.67701 | C11: =B11*Assumptions!$B$5 -> 7.6006205 | D11: =B11*Assumptions!$B$19 -> 3.8003102 | E11: =B11+C11-D11 -> 130.47732
A12: =A11+1 -> 10 | B12: =E11 -> 130.47732 | C12: =B12*Assumptions!$B$5 -> 7.8286391 | D12: =B12*Assumptions!$B$19 -> 3.9143196 | E12: =B12+C12-D12 -> 134.39164
A13: =A12+1 -> 11 | B13: =E12 -> 134.39164 | C13: =B13*Assumptions!$B$5 -> 8.0634983 | D13: =B13*Assumptions!$B$19 -> 4.0317491 | E13: =B13+C13-D13 -> 138.42339
A14: =A13+1 -> 12 | B14: =E13 -> 138.42339 | C14: =B14*Assumptions!$B$5 -> 8.3054032 | D14: =B14*Assumptions!$B$19 -> 4.1527016 | E14: =B14+C14-D14 -> 142.57609
A15: =A14+1 -> 13 | B15: =E14 -> 142.57609 | C15: =B15*Assumptions!$B$5 -> 8.5545653 | D15: =B15*Assumptions!$B$19 -> 4.2772827 | E15: =B15+C15-D15 -> 146.85337
... A38: =A37+1 -> 36 | B38: =E37 -> 281.38625 | C38: =B38*Assumptions!$B$5 -> 16.883175 | D38: =B38*Assumptions!$B$19 -> 8.4415874 | E38: =B38+C38-D38 -> 289.82783

Sheet Revenue_Model
A1: Month | B1: Customers | C1: Revenue
A3: 1 | B3: =Assumptions!$B$3 -> 100 | C3: =B3*Assumptions!$B$7 -> 50000
A4: 2 | B4: =Customer_Model!E3 -> 103 | C4: =B4*Assumptions!$B$7 -> 51500
A5: 3 | B5: =Customer_Model!E4 -> 106.09 | C5: =B5*Assumptions!$B$7 -> 53045
A6: 4 | B6: =Customer_Model!E5 -> 109.2727 | C6: =B6*Assumptions!$B$7 -> 54636.35
A7: 5 | B7: =Customer_Model!E6 -> 112.55088 | C7: =B7*Assumptions!$B$7 -> 56275.44
A8: 6 | B8: =Customer_Model!E7 -> 115.92741 | C8: =B8*Assumptions!$B$7 -> 57963.704
A9: 7 | B9: =Customer_Model!E8 -> 119.40523 | C9: =B9*Assumptions!$B$7 -> 59702.615
A10: 8 | B10: =Customer_Model!E9 -> 122.98739 | C10: =B10*Assumptions!$B$7 -> 61493.693
A11: 9 | B11: =Customer_Model!E10 -> 126.67701 | C11: =B11*Assumptions!$B$7 -> 63338.504
A12: 10 | B12: =Customer_Model!E11 -> 130.47732 | C12: =B12*Assumptions!$B$7 -> 65238.659
A13: 11 | B13: =Customer_Model!E12 -> 134.39164 | C13: =B13*Assumptions!$B$7 -> 67195.819
A14: 12 | B14: =Customer_Model!E13 -> 138.42339 | C14: =B14*Assumptions!$B$7 -> 69211.694
A15: 13 | B15: =Customer_Model!E14 -> 142.57609 | C15: =B15*Assumptions!$B$7 -> 71288.044
... A38: 36 | B38: =Customer_Model!E37 -> 281.38625 | C38: =B38*Assumptions!$B$7 -> 140693.12

Sheet Cost_Model
A1: Month | B1: Customers | C1: Variable Cost | D1: Fixed Cost | E1: Marketing Cost | F1: Total Cost
A3: =Revenue_Model!A3 -> 1 | B3: =Revenue_Model!B3 -> 100 | C3: =B3*Assumptions!$B$9 -> 15000 | D3: =Assumptions!$B$11 -> 20000 | E3: =Assumptions!$B$13 -> 8000 | F3: =C3+D3+E3 -> 43000
A4: =Revenue_Model!A4 -> 2 | B4: =Revenue_Model!B4 -> 103 | C4: =B4*Assumptions!$B$9 -> 15450 | D4: =Assumptions!$B$11 -> 20000 | E4: =Assumptions!$B$13 -> 8000 | F4: =C4+D4+E4 -> 43450
A5: =Revenue_Model!A5 -> 3 | B5: =Revenue_Model!B5 -> 106.09 | C5: =B5*Assumptions!$B$9 -> 15913.5 | D5: =Assumptions!$B$11 -> 20000 | E5: =Assumptions!$B$13 -> 8000 | F5: =C5+D5+E5 -> 43913.5
A6: =Revenue_Model!A6 -> 4 | B6: =Revenue_Model!B6 -> 109.2727 | C6: =B6*Assumptions!$B$9 -> 16390.905 | D6: =Assumptions!$B$11 -> 20000 | E6: =Assumptions!$B$13 -> 8000 | F6: =C6+D6+E6 -> 44390.905
A7: =Revenue_Model!A7 -> 5 | B7: =Revenue_Model!B7 -> 112.55088 | C7: =B7*Assumptions!$B$9 -> 16882.632 | D7: =Assumptions!$B$11 -> 20000 | E7: =Assumptions!$B$13 -> 8000 | F7: =C7+D7+E7 -> 44882.632
A8: =Revenue_Model!A8 -> 6 | B8: =Revenue_Model!B8 -> 115.92741 | C8: =B8*Assumptions!$B$9 -> 17389.111 | D8: =Assumptions!$B$11 -> 20000 | E8: =Assumptions!$B$13 -> 8000 | F8: =C8+D8+E8 -> 45389.111
A9: =Revenue_Model!A9 -> 7 | B9: =Revenue_Model!B9 -> 119.40523 | C9: =B9*Assumptions!$B$9 -> 17910.784 | D9: =Assumptions!$B$11 -> 20000 | E9: =Assumptions!$B$13 -> 8000 | F9: =C9+D9+E9 -> 45910.784
A10: =Revenue_Model!A10 -> 8 | B10: =Revenue_Model!B10 -> 122.98739 | C10: =B10*Assumptions!$B$9 -> 18448.108 | D10: =Assumptions!$B$11 -> 20000 | E10: =Assumptions!$B$13 -> 8000 | F10: =C10+D10+E10 -> 46448.108
A11: =Revenue_Model!A11 -> 9 | B11: =Revenue_Model!B11 -> 126.67701 | C11: =B11*Assumptions!$B$9 -> 19001.551 | D11: =Assumptions!$B$11 -> 20000 | E11: =Assumptions!$B$13 -> 8000 | F11: =C11+D11+E11 -> 47001.551
A12: =Revenue_Model!A12 -> 10 | B12: =Revenue_Model!B12 -> 130.47732 | C12: =B12*Assumptions!$B$9 -> 19571.598 | D12: =Assumptions!$B$11 -> 20000 | E12: =Assumptions!$B$13 -> 8000 | F12: =C12+D12+E12 -> 47571.598
A13: =Revenue_Model!A13 -> 11 | B13: =Revenue_Model!B13 -> 134.39164 | C13: =B13*Assumptions!$B$9 -> 20158.746 | D13: =Assumptions!$B$11 -> 20000 | E13: =Assumptions!$B$13 -> 8000 | F13: =C13+D13+E13 -> 48158.746
A14: =Revenue_Model!A14 -> 12 | B14: =Revenue_Model!B14 -> 138.42339 | C14: =B14*Assumptions!$B$9 -> 20763.508 | D14: =Assumptions!$B$11 -> 20000 | E14: =Assumptions!$B$13 -> 8000 | F14: =C14+D14+E14 -> 48763.508
... A38: =Revenue_Model!A38 -> 36 | B38: =Revenue_Model!B38 -> 281.38625 | C38: =B38*Assumptions!$B$9 -> 42207.937 | D38: =Assumptions!$B$11 -> 20000 | E38: =Assumptions!$B$13 -> 8000 | F38: =C38+D38+E38 -> 70207.937

Sheet Model_Calculations
A1: Month | B1: Revenue | C1: Total Cost | D1: Gross Profit | E1: Contribution Margin | F1: Break Even Customers | G1: Cumulative Profit
A3: 1 | B3: =Revenue_Model!C3 -> 50000 | C3: =Cost_Model!F3 -> 43000 | D3: =B3-C3 -> 7000 | E3: =Assumptions!$B$7-Assumptions!$B$9 -> 350 | F3: =Assumptions!$B$11/E3 -> 57.142857 | G3: =D3 -> 7000
A4: 2 | B4: =Revenue_Model!C4 -> 51500 | C4: =Cost_Model!F4 -> 43450 | D4: =B4-C4 -> 8050 | E4: =Assumptions!$B$7-Assumptions!$B$9 -> 350 | F4: =Assumptions!$B$11/E4 -> 57.142857 | G4: =G3+D4 -> 15050
A5: 3 | B5: =Revenue_Model!C5 -> 53045 | C5: =Cost_Model!F5 -> 43913.5 | D5: =B5-C5 -> 9131.5 | E5: =Assumptions!$B$7-Assumptions!$B$9 -> 350 | F5: =Assumptions!$B$11/E5 -> 57.142857 | G5: =G4+D5 -> 24181.5
A6: 4 | B6: =Revenue_Model!C6 -> 54636.35 | C6: =Cost_Model!F6 -> 44390.905 | D6: =B6-C6 -> 10245.445 | E6: =Assumptions!$B$7-Assumptions!$B$9 -> 350 | F6: =Assumptions!$B$11/E6 -> 57.142857 | G6: =G5+D6 -> 34426.945
A7: 5 | B7: =Revenue_Model!C7 -> 56275.44 | C7: =Cost_Model!F7 -> 44882.632 | D7: =B7-C7 -> 11392.808 | E7: =Assumptions!$B$7-Assumptions!$B$9 -> 350 | F7: =Assumptions!$B$11/E7 -> 57.142857 | G7: =G6+D7 -> 45819.753
A8: 6 | B8: =Revenue_Model!C8 -> 57963.704 | C8: =Cost_Model!F8 -> 45389.111 | D8: =B8-C8 -> 12574.593 | E8: =Assumptions!$B$7-Assumptions!$B$9 -> 350 | F8: =Assumptions!$B$11/E8 -> 57.142857 | G8: =G7+D8 -> 58394.346
A9: 7 | B9: =Revenue_Model!C9 -> 59702.615 | C9: =Cost_Model!F9 -> 45910.784 | D9: =B9-C9 -> 13791.83 | E9: =Assumptions!$B$7-Assumptions!$B$9 -> 350 | F9: =Assumptions!$B$11/E9 -> 57.142857 | G9: =G8+D9 -> 72186.176
A10: 8 | B10: =Revenue_Model!C10 -> 61493.693 | C10: =Cost_Model!F10 -> 46448.108 | D10: =B10-C10 -> 15045.585 | E10: =Assumptions!$B$7-Assumptions!$B$9 -> 350 | F10: =Assumptions!$B$11/E10 -> 57.142857 | G10: =G9+D10 -> 87231.762
A11: 9 | B11: =Revenue_Model!C11 -> 63338.504 | C11: =Cost_Model!F11 -> 47001.551 | D11: =B11-C11 -> 16336.953 | E11: =Assumptions!$B$7-Assumptions!$B$9 -> 350 | F11: =Assumptions!$B$11/E11 -> 57.142857 | G11: =G10+D11 -> 103568.71
A12: 10 | B12: =Revenue_Model!C12 -> 65238.659 | C12: =Cost_Model!F12 -> 47571.598 | D12: =B12-C12 -> 17667.061 | E12: =Assumptions!$B$7-Assumptions!$B$9 -> 350 | F12: =Assumptions!$B$11/E12 -> 57.142857 | G12: =G11+D12 -> 121235.78
A13: 11 | B13: =Revenue_Model!C13 -> 67195.819 | C13: =Cost_Model!F13 -> 48158.746 | D13: =B13-C13 -> 19037.073 | E13: =Assumptions!$B$7-Assumptions!$B$9 -> 350 | F13: =Assumptions!$B$11/E13 -> 57.142857 | G13: =G12+D13 -> 140272.85
A14: 12 | B14: =Revenue_Model!C14 -> 69211.694 | C14: =Cost_Model!F14 -> 48763.508 | D14: =B14-C14 -> 20448.185 | E14: =Assumptions!$B$7-Assumptions!$B$9 -> 350 | F14: =Assumptions!$B$11/E14 -> 57.142857 | G14: =G13+D14 -> 160721.03
A15: 13 | B15: =Revenue_Model!C15 -> 71288.044 | C15: =Cost_Model!F15 -> 49386.413 | D15: =B15-C15 -> 21901.631 | E15: =Assumptions!$B$7-Assumptions!$B$9 -> 350 | F15: =Assumptions!$B$11/E15 -> 57.142857 | G15: =G14+D15 -> 182622.67
... A38: 36 | B38: =Revenue_Model!C38 -> 140693.12 | C38: =Cost_Model!F38 -> 70207.937 | D38: =B38-C38 -> 70485.186 | E38: =Assumptions!$B$7-Assumptions!$B$9 -> 350 | F38: =Assumptions!$B$11/E38 -> 57.142857 | G38: =G37+D38 -> 1206658

Sheet Unit_Economics
A1: Metric | B1: Formula | C1: Value
A3: Marketing Spend | B3: Assumptions | C3: =Assumptions!$B$13 -> 8000
A4: New Customers | B4: Customer_Model | C4: =AVERAGE(Customer_Model!C3:C38) -> 10.545991
A5: CAC | B5: CAC = Marketing Spend / New Customers | C5: =C3/C4 -> 758.58212
A6: LTV | B6: LTV = Price per Customer / Churn Rate | C6: =Assumptions!$B$7 / Assumptions!$B$19 -> 16666.667
A7: LTV/CAC Ratio | C7: =C6/C5 -> 21.970814

Sheet Profit_Loss
A1: Month | B1: Revenue | C1: Total Cost | D1: Profit Before Tax | E1: Tax | F1: Net Profit
A3: 1 | B3: =Revenue_Model!C3 -> 50000 | C3: =Cost_Model!F3 -> 43000 | D3: =B3 - C3 -> 7000 | E3: =D3 *Assumptions!$B$15 -> 1750 | F3: =D3 - E3 -> 5250
A4: 2 | B4: =Revenue_Model!C4 -> 51500 | C4: =Cost_Model!F4 -> 43450 | D4: =B4 - C4 -> 8050 | E4: =D4 *Assumptions!$B$15 -> 2012.5 | F4: =D4 - E4 -> 6037.5
A5: 3 | B5: =Revenue_Model!C5 -> 53045 | C5: =Cost_Model!F5 -> 43913.5 | D5: =B5 - C5 -> 9131.5 | E5: =D5 *Assumptions!$B$15 -> 2282.875 | F5: =D5 - E5 -> 6848.625
A6: 4 | B6: =Revenue_Model!C6 -> 54636.35 | C6: =Cost_Model!F6 -> 44390.905 | D6: =B6 - C6 -> 10245.445 | E6: =D6 *Assumptions!$B$15 -> 2561.3612 | F6: =D6 - E6 -> 7684.0837
A7: 5 | B7: =Revenue_Model!C7 -> 56275.44 | C7: =Cost_Model!F7 -> 44882.632 | D7: =B7 - C7 -> 11392.808 | E7: =D7 *Assumptions!$B$15 -> 2848.2021 | F7: =D7 - E7 -> 8544.6063
A8: 6 | B8: =Revenue_Model!C8 -> 57963.704 | C8: =Cost_Model!F8 -> 45389.111 | D8: =B8 - C8 -> 12574.593 | E8: =D8 *Assumptions!$B$15 -> 3143.6482 | F8: =D8 - E8 -> 9430.9445
A9: 7 | B9: =Revenue_Model!C9 -> 59702.615 | C9: =Cost_Model!F9 -> 45910.784 | D9: =B9 - C9 -> 13791.83 | E9: =D9 *Assumptions!$B$15 -> 3447.9576 | F9: =D9 - E9 -> 10343.873
A10: 8 | B10: =Revenue_Model!C10 -> 61493.693 | C10: =Cost_Model!F10 -> 46448.108 | D10: =B10 - C10 -> 15045.585 | E10: =D10 *Assumptions!$B$15 -> 3761.3963 | F10: =D10 - E10 -> 11284.189
A11: 9 | B11: =Revenue_Model!C11 -> 63338.504 | C11: =Cost_Model!F11 -> 47001.551 | D11: =B11 - C11 -> 16336.953 | E11: =D11 *Assumptions!$B$15 -> 4084.2382 | F11: =D11 - E11 -> 12252.715
A12: 10 | B12: =Revenue_Model!C12 -> 65238.659 | C12: =Cost_Model!F12 -> 47571.598 | D12: =B12 - C12 -> 17667.061 | E12: =D12 *Assumptions!$B$15 -> 4416.7654 | F12: =D12 - E12 -> 13250.296
A13: 11 | B13: =Revenue_Model!C13 -> 67195.819 | C13: =Cost_Model!F13 -> 48158.746 | D13: =B13 - C13 -> 19037.073 | E13: =D13 *Assumptions!$B$15 -> 4759.2683 | F13: =D13 - E13 -> 14277.805
A14: 12 | B14: =Revenue_Model!C14 -> 69211.694 | C14: =Cost_Model!F14 -> 48763.508 | D14: =B14 - C14 -> 20448.185 | E14: =D14 *Assumptions!$B$15 -> 5112.0464 | F14: =D14 - E14 -> 15336.139
... A38: 36 | B38: =Revenue_Model!C38 -> 140693.12 | C38: =Cost_Model!F38 -> 70207.937 | D38: =B38 - C38 -> 70485.186 | E38: =D38 *Assumptions!$B$15 -> 17621.296 | F38: =D38 - E38 -> 52863.889

Sheet Cash_Flow
A1: Month | B1: Revenue | C1: Total Cost | D1: Burn Rate | E1: Cash Balance
A3: 1 | B3: =Revenue_Model!C3 -> 50000 | C3: =Cost_Model!F3 -> 43000 | D3: =B3-C3 -> 7000 | E3: =Assumptions!B21 + D3 -> 507000
A4: 2 | B4: =Revenue_Model!C4 -> 51500 | C4: =Cost_Model!F4 -> 43450 | D4: =B4-C4 -> 8050 | E4: =E3 + D4 -> 515050
A5: 3 | B5: =Revenue_Model!C5 -> 53045 | C5: =Cost_Model!F5 -> 43913.5 | D5: =B5-C5 -> 9131.5 | E5: =E4 + D5 -> 524181.5
A6: 4 | B6: =Revenue_Model!C6 -> 54636.35 | C6: =Cost_Model!F6 -> 44390.905 | D6: =B6-C6 -> 10245.445 | E6: =E5 + D6 -> 534426.94
A7: 5 | B7: =Revenue_Model!C7 -> 56275.44 | C7: =Cost_Model!F7 -> 44882.632 | D7: =B7-C7 -> 11392.808 | E7: =E6 + D7 -> 545819.75
A8: 6 | B8: =Revenue_Model!C8 -> 57963.704 | C8: =Cost_Model!F8 -> 45389.111 | D8: =B8-C8 -> 12574.593 | E8: =E7 + D8 -> 558394.35
A9: 7 | B9: =Revenue_Model!C9 -> 59702.615 | C9: =Cost_Model!F9 -> 45910.784 | D9: =B9-C9 -> 13791.83 | E9: =E8 + D9 -> 572186.18
A10: 8 | B10: =Revenue_Model!C10 -> 61493.693 | C10: =Cost_Model!F10 -> 46448.108 | D10: =B10-C10 -> 15045.585 | E10: =E9 + D10 -> 587231.76
A11: 9 | B11: =Revenue_Model!C11 -> 63338.504 | C11: =Cost_Model!F11 -> 47001.551 | D11: =B11-C11 -> 16336.953 | E11: =E10 + D11 -> 603568.71
A12: 10 | B12: =Revenue_Model!C12 -> 65238.659 | C12: =Cost_Model!F12 -> 47571.598 | D12: =B12-C12 -> 17667.061 | E12: =E11 + D12 -> 621235.78
A13: 11 | B13: =Revenue_Model!C13 -> 67195.819 | C13: =Cost_Model!F13 -> 48158.746 | D13: =B13-C13 -> 19037.073 | E13: =E12 + D13 -> 640272.85
A14: 12 | B14: =Revenue_Model!C14 -> 69211.694 | C14: =Cost_Model!F14 -> 48763.508 | D14: =B14-C14 -> 20448.185 | E14: =E13 + D14 -> 660721.03
A15: 13 | B15: =Revenue_Model!C15 -> 71288.044 | C15: =Cost_Model!F15 -> 49386.413 | D15: =B15-C15 -> 21901.631 | E15: =E14 + D15 -> 682622.67
... A38: 36 | B38: =Revenue_Model!C38 -> 140693.12 | C38: =Cost_Model!F38 -> 70207.937 | D38: =B38-C38 -> 70485.186 | E38: =E37 + D38 -> 1706658

Sheet Sensitivity_Analysis
A1: Price | B1: Month 36 Net Profit (₹) | D1: Growth Rate | E1: Month 36 Net Profit (₹)
A2: 400 | B2: =(A2-Assumptions!$B$9)*(Assumptions!$B$3*(1+Assumptions!$B$5)^35)*(1-Assumptions!$B$15)-(Assumptions!$B$11+Assumptions!$B$13)*(1-Assumptions!$B$15) -> 123114.13 | D2: 0.03 | E2: =(Assumptions!$B$7-Assumptions!$B$9)*(Assumptions!$B$3*(1+D2)^35)*(1-Assumptions!$B$15)-(Assumptions!$B$11+Assumptions!$B$13)*(1-Assumptions!$B$15) -> 52863.889
A3: 450 | B3: =(A3-Assumptions!$B$9)*(Assumptions!$B$3*(1+Assumptions!$B$5)^35)*(1-Assumptions!$B$15)-(Assumptions!$B$11+Assumptions!$B$13)*(1-Assumptions!$B$15) -> 151936.95 | D3: 0.05 | E3: =(Assumptions!$B$7-Assumptions!$B$9)*(Assumptions!$B$3*(1+D3)^35)*(1-Assumptions!$B$15)-(Assumptions!$B$11+Assumptions!$B$13)*(1-Assumptions!$B$15) -> 123795.4
A4: 500 | B4: =(A4-Assumptions!$B$9)*(Assumptions!$B$3*(1+Assumptions!$B$5)^35)*(1-Assumptions!$B$15)-(Assumptions!$B$11+Assumptions!$B$13)*(1-Assumptions!$B$15) -> 180759.78 | D4: 0.06 | E4: =(Assumptions!$B$7-Assumptions!$B$9)*(Assumptions!$B$3*(1+D4)^35)*(1-Assumptions!$B$15)-(Assumptions!$B$11+Assumptions!$B$13)*(1-Assumptions!$B$15) -> 180759.78
A5: 550 | B5: =(A5-Assumptions!$B$9)*(Assumptions!$B$3*(1+Assumptions!$B$5)^35)*(1-Assumptions!$B$15)-(Assumptions!$B$11+Assumptions!$B$13)*(1-Assumptions!$B$15) -> 209582.6 | D5: 0.08 | E5: =(Assumptions!$B$7-Assumptions!$B$9)*(Assumptions!$B$3*(1+D5)^35)*(1-Assumptions!$B$15)-(Assumptions!$B$11+Assumptions!$B$13)*(1-Assumptions!$B$15) -> 367115.29
A6: 600 | B6: =(A6-Assumptions!$B$9)*(Assumptions!$B$3*(1+Assumptions!$B$5)^35)*(1-Assumptions!$B$15)-(Assumptions!$B$11+Assumptions!$B$13)*(1-Assumptions!$B$15) -> 238405.43 | D6: 0.1 | E6: =(Assumptions!$B$7-Assumptions!$B$9)*(Assumptions!$B$3*(1+D6)^35)*(1-Assumptions!$B$15)-(Assumptions!$B$11+Assumptions!$B$13)*(1-Assumptions!$B$15) -> 716688.97
A7: 650 | B7: =(A7-Assumptions!$B$9)*(Assumptions!$B$3*(1+Assumptions!$B$5)^35)*(1-Assumptions!$B$15)-(Assumptions!$B$11+Assumptions!$B$13)*(1-Assumptions!$B$15) -> 267228.25 | D7: 0.12 | E7: =(Assumptions!$B$7-Assumptions!$B$9)*(Assumptions!$B$3*(1+D7)^35)*(1-Assumptions!$B$15)-(Assumptions!$B$11+Assumptions!$B$13)*(1-Assumptions!$B$15) -> 1364990

Sheet Dashboard
A1: STARTUP FINANCIAL MODEL — KEY METRICS
A2: Metric | B2: Value | F2: KPI Summary (A1:E5)
A3: Total Revenue (Year 3) | B3: =SUM(Revenue_Model!C2:C37) -> 3023104.1 | F3: Revenue Growth | G3: Net Profit Growth
A4: Final Net Profit | B4: =SUM(Profit_Loss!F2:F37) -> 852129.65 | F4: Customer Growth | G4: Price Sensitivity
A5: Total Customers | B5: =Customer_Model!E38 -> 289.82783 | F5: Growth Rate Sensitivity
A6: Cash Balance | B6: =Cash_Flow!E38 -> 1706658
